toisan_lang/__init__.py
toisan_lang/__main__.py
toisan_lang/compiler.py
toisan_lang/grammar.py
toisan_lang/keyword.py
toisan_lang/node.py
toisan_lang-0.1.4.dist-info/LICENSE
toisan_lang-0.1.4.dist-info/METADATA
toisan_lang-0.1.4.dist-info/WHEEL
toisan_lang-0.1.4.dist-info/top_level.txt
toisan_lang-0.1.4.dist-info/RECORD
