Metadata-Version: 2.1
Name: toisan-lang
Version: 0.1.4
Summary: A programming language based on Toisanese, aka Taishanese, a dialect of Cantonese
Author-email: Zeheng Li <imzehengl@gmail.com>
Maintainer-email: Zeheng Li <imzehengl@gmail.com>
Project-URL: repository, https://github.com/zehengl/toisan-lang
Project-URL: homepage, https://zehengl.github.io/toisan-lang/
Keywords: Toisan,Taishan
Classifier: Programming Language :: Python :: 3
Classifier: License :: OSI Approved :: MIT License
Classifier: Operating System :: OS Independent
Requires-Python: >=3.8
License-File: LICENSE
Requires-Dist: lrparsing ==1.0.13
